<?xml version="1.0" encoding="UTF-8"?>
<?eclipse version="3.0"?>

 <plugin>

  <!-- EEF extensions -->
  <extension
         point="org.eclipse.emf.eef.runtime.PropertiesEditionProvider">
      <PropertiesEditionComponentProvider
            providerClass="net.certware.verification.checklist.providers.ChecklistPackagePropertiesEditionProvider">
      </PropertiesEditionComponentProvider>
   </extension>
   <extension
         point="org.eclipse.emf.eef.runtime.PropertiesEditionPolicyProvider">
      <PropertiesEditionPolicyProvider
            providerClass="net.certware.verification.checklist.providers.ChecklistPackagePropertiesEditionPolicyProvider">
      </PropertiesEditionPolicyProvider>
   </extension>
   <extension
         point="org.eclipse.emf.eef.runtime.PropertiesEditionPartProvider">
      <PropertiesEditionPartProvider
            providerClass="net.certware.verification.checklist.providers.ChecklistPropertiesEditionPartProvider">
      </PropertiesEditionPartProvider>
   </extension>

   <!-- Tabbed properties views extension -->
   <extension
         point="org.eclipse.ui.views.properties.tabbed.propertyContributor">
      <propertyContributor
            contributorId="net.certware.verification.checklist.properties">
         <propertyCategory
               category="default">
         </propertyCategory>
         <propertyCategory
               category="extended">
         </propertyCategory>
         <propertyCategory
               category="advanced">
         </propertyCategory>
      </propertyContributor>
   </extension>
   <extension
         point="org.eclipse.ui.views.properties.tabbed.propertyTabs">
      <propertyTabs
            contributorId="net.certware.verification.checklist.properties">
         <propertyTab
               label="Base"
               category="default"
               id="Base">
         </propertyTab>
      </propertyTabs>
   </extension>
   <extension
         point="org.eclipse.ui.views.properties.tabbed.propertySections">
      <propertySections
            contributorId="net.certware.verification.checklist.properties">
         <propertySection
               class="org.eclipse.emf.eef.runtime.ui.properties.sections.PropertiesEditionSection"
               id="net.certware.verification.checklist.section.Category"
               tab="Base">
             <input
                    type="net.certware.verification.checklist.Category">
             </input>
         </propertySection>
         <propertySection
               class="org.eclipse.emf.eef.runtime.ui.properties.sections.PropertiesEditionSection"
               id="net.certware.verification.checklist.section.Item"
               tab="Base">
             <input
                    type="net.certware.verification.checklist.Item">
             </input>
         </propertySection>
         <propertySection
               class="org.eclipse.emf.eef.runtime.ui.properties.sections.PropertiesEditionSection"
               id="net.certware.verification.checklist.section.Checklist"
               tab="Base">
             <input
                    type="net.certware.verification.checklist.Checklist">
             </input>
         </propertySection>
      </propertySections>
   </extension>
 </plugin>
